{
  "1": {
    "chargeCampEffectID": "1",
    "effectID": "31",
    "levelIncrease": "3",
    "maxValue": "450"
  },
  "2": {
    "chargeCampEffectID": "2",
    "effectID": "32",
    "levelIncrease": "3",
    "maxValue": "450"
  },
  "3": {
    "chargeCampEffectID": "3",
    "effectID": "33",
    "levelIncrease": "1",
    "maxValue": "200"
  },
  "4": {
    "chargeCampEffectID": "4",
    "effectID": "34",
    "levelIncrease": "3",
    "maxValue": "450"
  },
  "5": {
    "chargeCampEffectID": "5",
    "effectID": "35",
    "levelIncrease": "3",
    "maxValue": "450"
  },
  "6": {
    "chargeCampEffectID": "6",
    "effectID": "36",
    "levelIncrease": "2",
    "maxValue": "400"
  },
  "7": {
    "chargeCampEffectID": "7",
    "effectID": "37",
    "levelIncrease": "1",
    "maxValue": "150"
  }
}